MagInv/Call_Matrix.py
MagInv/Inversion.py
MagInv/Total_Anomaly.py
MagInv/__init__.py
MagInv/boundary.py
MagInv/visualization.py
MagInv-0.0.1.dist-info/METADATA
MagInv-0.0.1.dist-info/WHEEL
MagInv-0.0.1.dist-info/top_level.txt
MagInv-0.0.1.dist-info/RECORD
