Metadata-Version: 2.1
Name: MagInv
Version: 0.0.1
Summary: A Python library for magnetic inversion, including data processing.
Author: Nimatullah
Author-email: naimatullah1804@gmail.com
Classifier: Programming Language :: Python :: 3
Classifier: Programming Language :: Python :: 3.8
Classifier: License :: OSI Approved :: MIT License
Classifier: Operating System :: OS Independent
Requires-Python: >=3.6
Requires-Dist: numpy
Requires-Dist: scipy
Requires-Dist: matplotlib
Requires-Dist: joblib
Requires-Dist: plotly
